electron_configuration/__init__.py
electron_configuration/configuration.py
electron_configuration/main.py
tests/__init__.py
tests/test.py
electron_configuration-0.2.dist-info/LICENSE
electron_configuration-0.2.dist-info/METADATA
electron_configuration-0.2.dist-info/WHEEL
electron_configuration-0.2.dist-info/top_level.txt
electron_configuration-0.2.dist-info/RECORD
