Metadata-Version: 2.1
Name: electron-configuration
Version: 0.2
Summary: A library to get the electron configuration of elements
Author: Jay Jethwa
Classifier: Programming Language :: Python :: 3
Classifier: License :: OSI Approved :: MIT License
Classifier: Operating System :: OS Independent
Requires-Python: >=3.6
License-File: LICENSE
